nlt/__init__.py
nlt/numlet.py
numlet-2.0.0.dist-info/LICENSE
numlet-2.0.0.dist-info/METADATA
numlet-2.0.0.dist-info/WHEEL
numlet-2.0.0.dist-info/top_level.txt
numlet-2.0.0.dist-info/RECORD
