Metadata-Version: 2.1
Name: numlet
Version: 2.0.0
Summary: Convierte a letras más de 10^600 números
Home-page: https://github.com/roylanmartinez/Numlet
Author: Roylan Martinez Vargas
Author-email: roylanmartinez97@gmail.com
License: UNKNOWN
Platform: UNKNOWN
Classifier: Programming Language :: Python :: 3
Classifier: License :: OSI Approved :: MIT License
Classifier: Operating System :: OS Independent
Requires-Python: >=3.6
